Metadata-Version: 2.1
Name: notifymanager
Version: 0.0.1
Summary: manage notifications in python
Home-page: https://github.com/iperera97/notifymanager
Author: isuru perera
Author-email: isurumahesh97@gmail.com
License: UNKNOWN
Platform: UNKNOWN
